odoo/addons/account_bank_statement_import_qif/README.rst
odoo/addons/account_bank_statement_import_qif/__init__.py
odoo/addons/account_bank_statement_import_qif/__manifest__.py
odoo/addons/account_bank_statement_import_qif/i18n/account_bank_statement_import_qif.pot
odoo/addons/account_bank_statement_import_qif/i18n/de.po
odoo/addons/account_bank_statement_import_qif/i18n/es.po
odoo/addons/account_bank_statement_import_qif/i18n/fa.po
odoo/addons/account_bank_statement_import_qif/i18n/fi.po
odoo/addons/account_bank_statement_import_qif/i18n/fr.po
odoo/addons/account_bank_statement_import_qif/i18n/fr_CH.po
odoo/addons/account_bank_statement_import_qif/i18n/gl.po
odoo/addons/account_bank_statement_import_qif/i18n/hr.po
odoo/addons/account_bank_statement_import_qif/i18n/lt_LT.po
odoo/addons/account_bank_statement_import_qif/i18n/nb_NO.po
odoo/addons/account_bank_statement_import_qif/i18n/nl.po
odoo/addons/account_bank_statement_import_qif/i18n/pt_BR.po
odoo/addons/account_bank_statement_import_qif/i18n/pt_PT.po
odoo/addons/account_bank_statement_import_qif/i18n/sl.po
odoo/addons/account_bank_statement_import_qif/static/description/icon.png
odoo/addons/account_bank_statement_import_qif/tests/__init__.py
odoo/addons/account_bank_statement_import_qif/tests/test_import_bank_statement.py
odoo/addons/account_bank_statement_import_qif/tests/test_qif.qif
odoo/addons/account_bank_statement_import_qif/wizards/__init__.py
odoo/addons/account_bank_statement_import_qif/wizards/account_bank_statement_import_qif.py
odoo/addons/account_bank_statement_import_qif/wizards/account_bank_statement_import_qif_view.xml
odoo11_addon_account_bank_statement_import_qif-11.0.1.0.1.dist-info/METADATA
odoo11_addon_account_bank_statement_import_qif-11.0.1.0.1.dist-info/RECORD
odoo11_addon_account_bank_statement_import_qif-11.0.1.0.1.dist-info/WHEEL
odoo11_addon_account_bank_statement_import_qif-11.0.1.0.1.dist-info/top_level.txt
